xain_sdk/__init__.py
xain_sdk/__version__.py
xain_sdk/http.py
xain_sdk/participant.py
xain_sdk/utils.py
xain_sdk-0.8.0.dist-info/METADATA
xain_sdk-0.8.0.dist-info/WHEEL
xain_sdk-0.8.0.dist-info/top_level.txt
xain_sdk-0.8.0.dist-info/RECORD
