Metadata-Version: 2.1
Name: xain-sdk
Version: 0.8.0
Summary: XAIN is an open source framework for federated learning.
Home-page: https://github.com/xainag/xain-sdk
Author: ['XAIN AG']
Author-email: engineering@xain.io
License: Apache License Version 2.0
Platform: UNKNOWN
Requires-Python: >=3.6
Requires-Dist: requests
Requires-Dist: numpy
Provides-Extra: dev
Requires-Dist: black ; extra == 'dev'
Requires-Dist: mypy ; extra == 'dev'
Requires-Dist: pylint ; extra == 'dev'
Requires-Dist: isort ; extra == 'dev'
Requires-Dist: pip-licenses ; extra == 'dev'
Requires-Dist: pytest ; extra == 'dev'
Requires-Dist: Sphinx (~=2.2) ; extra == 'dev'
Requires-Dist: m2r (~=0.2) ; extra == 'dev'
Requires-Dist: sphinxcontrib-mermaid (~=0.3) ; extra == 'dev'
Requires-Dist: sphinx-autodoc-typehints (~=1.10) ; extra == 'dev'
Requires-Dist: docutils (~=0.16) ; extra == 'dev'
Provides-Extra: docs
Requires-Dist: Sphinx (~=2.2) ; extra == 'docs'
Requires-Dist: m2r (~=0.2) ; extra == 'docs'
Requires-Dist: sphinxcontrib-mermaid (~=0.3) ; extra == 'docs'
Requires-Dist: sphinx-autodoc-typehints (~=1.10) ; extra == 'docs'
Requires-Dist: docutils (~=0.16) ; extra == 'docs'
Provides-Extra: test
Requires-Dist: pytest ; extra == 'test'
